{
    "2018": {
        "Jul": {
            "2": {
                "Mon": {
                    "Call": {
                        "1": "MI",
                        "2": "SK"
                    },
                    "Admin": 1,
                    "Requests": "MI 1st",
                    "Offsite": [
                        "TT",
                        "TT",
                        "X",
                        "SL",
                        "DD",
                        "RK",
                        "TI",
                        "JM",
                        "CM"
                    ]
                }
            },
            "3": {
                "Tue": {
                    "Call": {
                        "1": "DN",
                        "2": "CA"
                    },
                    "Admin": 1,
                    "Offsite": [
                        "MA",
                        "DD",
                        "RK",
                        "TI",
                        "JM",
                        "CM"
                    ]
                }
            },
            "4": {
                "Wed": {
                    "Call": {
                        "1": "CA",
                        "2": "DN"
                    },
                    "Admin": 1,
                    "Offsite": [
                        "MA",
                        "DD",
                        "TI",
                        "JM",
                        "CM"
                    ]
                }
            },
            "5": {
                "Thu": {
                    "Call": {
                        "1": "MC",
                        "2": "PM"
                    },
                    "Admin": 1,
                    "Requests": "MC on",
                    "Offsite": [
                        "RR",
                        "DD",
                        "RK",
                        "TI",
                        "JM",
                        "CM"
                    ]
                }
            },
            "6": {
                "Fri": {
                    "Call": {
                        "1": "FM",
                        "2": "SK"
                    },
                    "Admin": 1,
                    "Offsite": [
                        "TT",
                        "DD",
                        "RK",
                        "TI",
                        "JM",
                        "CM"
                    ]
                }
            },
            "7": {
                "Sat AM": {
                    "Call": {
                        "1": "JT",
                        "2": "SK"
                    },
                    "Admin": 0,
                    "Offsite": [
                        "TT",
                        "SK"
                    ]
                },
                "Sat PM": {
                    "Call": {
                        "1": "SK",
                        "2": "JT"
                    },
                    "Admin": 0,
                    "Offsite": [
                        "TT"
                    ]
                }
            },
            "8": {
                "Sun AM": {
                    "Call": {
                        "1": "FM",
                        "2": "SK"
                    },
                    "Admin": 0,
                    "Requests": "RK off",
                    "Offsite": [
                        "TT"
                    ]
                },
                "Sun PM": {
                    "Call": {
                        "1": "JT",
                        "2": "SK"
                    },
                    "Admin": 0,
                    "Offsite": [
                        "TT"
                    ]
                }
            },
            "9": {
                "Mon": {
                    "Call": {
                        "1": "JM",
                        "2": "JJ"
                    },
                    "Admin": 1,
                    "Offsite": [
                        "MA",
                        "TI",
                        "TT",
                        "X",
                        "SL",
                        "MC",
                        "RR",
                        "CM",
                        "CA",
                        "PM"
                    ]
                }
            },
            "10": {
                "Tue": {
                    "Call": {
                        "1": "KK",
                        "2": "ES"
                    },
                    "Admin": 1,
                    "Offsite": [
                        "TI",
                        "MC",
                        "RR",
                        "CM",
                        "CA",
                        "PM"
                    ]
                }
            },
            "11": {
                "Wed": {
                    "Call": {
                        "1": "JT",
                        "2": "CC"
                    },
                    "Admin": 1,
                    "Offsite": [
                        "TT",
                        "MC",
                        "RR",
                        "CM",
                        "CA",
                        "PM"
                    ]
                }
            },
            "12": {
                "Thu": {
                    "Call": {
                        "1": "SK",
                        "2": "RK"
                    },
                    "Admin": 1,
                    "Requests": "MI off",
                    "Offsite": [
                        "MA",
                        "MC",
                        "RR",
                        "CM",
                        "CA",
                        "PM"
                    ]
                }
            },
            "13": {
                "Fri": {
                    "Call": {
                        "1": "JM",
                        "2": "DN"
                    },
                    "Admin": 1,
                    "Offsite": [
                        "TI",
                        "MC",
                        "RR",
                        "CM",
                        "CA",
                        "PM"
                    ]
                }
            },
            "14": {
                "Sat AM": {
                    "Call": {
                        "1": "MI",
                        "2": "DN"
                    },
                    "Admin": 0,
                    "Requests": "JM Fri/Sun",
                    "Offsite": [
                        "TI",
                        "DN"
                    ]
                },
                "Sat PM": {
                    "Call": {
                        "1": "DN",
                        "2": "MI"
                    },
                    "Admin": 0,
                    "Offsite": [
                        "TI"
                    ]
                }
            },
            "15": {
                "Sun AM": {
                    "Call": {
                        "1": "JM",
                        "2": "DN"
                    },
                    "Admin": 0,
                    "Offsite": [
                        "TI"
                    ]
                },
                "Sun PM": {
                    "Call": {
                        "1": "MI",
                        "2": "DN"
                    },
                    "Admin": 0,
                    "Offsite": [
                        "TI"
                    ]
                }
            },
            "16": {
                "Mon": {
                    "Call": {
                        "1": "KK",
                        "2": "SL"
                    },
                    "Admin": 1,
                    "Offsite": [
                        "CM",
                        "TI",
                        "X",
                        "SK",
                        "ES",
                        "MA",
                        "JJ",
                        "CA",
                        "RK"
                    ]
                }
            },
            "17": {
                "Tue": {
                    "Call": {
                        "1": "FM",
                        "2": "MC"
                    },
                    "Admin": 1,
                    "Requests": "FM or SK on",
                    "Offsite": [
                        "RR",
                        "ES",
                        "MA",
                        "JJ",
                        "CA",
                        "RK"
                    ]
                }
            },
            "18": {
                "Wed": {
                    "Call": {
                        "1": "JM",
                        "2": "PM"
                    },
                    "Admin": 1,
                    "Offsite": [
                        "TI",
                        "ES",
                        "MA",
                        "JJ",
                        "CA",
                        "RK"
                    ]
                }
            },
            "19": {
                "Thu": {
                    "Call": {
                        "1": "DN",
                        "2": "JT"
                    },
                    "Admin": 1,
                    "Requests": "DN 1st, JT 2nd",
                    "Offsite": [
                        "CM",
                        "ES",
                        "MA",
                        "JJ",
                        "CA",
                        "RK"
                    ]
                }
            },
            "20": {
                "Fri": {
                    "Call": {
                        "1": "MC",
                        "2": "CC"
                    },
                    "Admin": 1,
                    "Offsite": [
                        "RR",
                        "ES",
                        "MA",
                        "JJ",
                        "CA",
                        "RK"
                    ]
                }
            },
            "21": {
                "Sat AM": {
                    "Call": {
                        "1": "KK",
                        "2": "CC"
                    },
                    "Admin": 0,
                    "Requests": "PM off",
                    "Offsite": [
                        "RR",
                        "CC"
                    ]
                },
                "Sat PM": {
                    "Call": {
                        "1": "CC",
                        "2": "KK"
                    },
                    "Admin": 0,
                    "Offsite": [
                        "RR"
                    ]
                }
            },
            "22": {
                "Sun AM": {
                    "Call": {
                        "1": "MC",
                        "2": "CC"
                    },
                    "Admin": 0,
                    "Offsite": [
                        "RR"
                    ]
                },
                "Sun PM": {
                    "Call": {
                        "1": "KK",
                        "2": "CC"
                    },
                    "Admin": 0,
                    "Offsite": [
                        "RR"
                    ]
                }
            },
            "23": {
                "Mon": {
                    "Call": {
                        "1": "FM",
                        "2": "RK"
                    },
                    "Admin": 1,
                    "Offsite": [
                        "CM",
                        "TT",
                        "SK",
                        "JM",
                        "ES",
                        "DD",
                        "JT",
                        "DN"
                    ]
                }
            },
            "24": {
                "Tue": {
                    "Call": {
                        "1": "PM",
                        "2": "JJ"
                    },
                    "Admin": 1,
                    "Offsite": [
                        "MA",
                        "JM",
                        "ES",
                        "DD",
                        "JT",
                        "DN"
                    ]
                }
            },
            "25": {
                "Wed": {
                    "Call": {
                        "1": "SL",
                        "2": "KK"
                    },
                    "Admin": 1,
                    "Offsite": [
                        "RR",
                        "JM",
                        "ES",
                        "DD",
                        "JT",
                        "DN"
                    ]
                }
            },
            "26": {
                "Thu": {
                    "Call": {
                        "1": "CC",
                        "2": "FM"
                    },
                    "Admin": 1,
                    "Requests": "CC 1st",
                    "Offsite": [
                        "TT",
                        "JM",
                        "ES",
                        "DD",
                        "JT",
                        "DN"
                    ]
                }
            },
            "27": {
                "Fri": {
                    "Call": {
                        "1": "JJ",
                        "2": "RK"
                    },
                    "Admin": 1,
                    "Offsite": [
                        "CM",
                        "JM",
                        "ES",
                        "DD",
                        "JT",
                        "DN"
                    ]
                }
            },
            "28": {
                "Sat AM": {
                    "Call": {
                        "1": "PM",
                        "2": "RK"
                    },
                    "Admin": 0,
                    "Requests": "SL, CA, FM/SK off",
                    "Offsite": [
                        "CM",
                        "RK"
                    ]
                },
                "Sat PM": {
                    "Call": {
                        "1": "RK",
                        "2": "PM"
                    },
                    "Admin": 0,
                    "Offsite": [
                        "CM"
                    ]
                }
            },
            "29": {
                "Sun AM": {
                    "Call": {
                        "1": "JJ",
                        "2": "RK"
                    },
                    "Admin": 0,
                    "Offsite": [
                        "CM"
                    ]
                },
                "Sun PM": {
                    "Call": {
                        "1": "PM",
                        "2": "RK"
                    },
                    "Admin": 0,
                    "Offsite": [
                        "CM"
                    ]
                }
            },
            "30": {
                "Mon": {
                    "Call": {
                        "1": "SK",
                        "2": "TI"
                    },
                    "Admin": 1,
                    "Offsite": [
                        "RR",
                        "X",
                        "KK",
                        "DN",
                        "JT",
                        "ES",
                        "MI",
                        "TT"
                    ]
                }
            },
            "31": {
                "Tue": {
                    "Call": {
                        "1": "SL",
                        "2": "JM"
                    },
                    "Admin": 1,
                    "Offsite": [
                        "MA",
                        "DN",
                        "JT",
                        "ES",
                        "MI",
                        "TT"
                    ]
                }
            }
        },
        "Aug": {
            "1": {
                "Wed": {
                    "Call": {
                        "1": "CC",
                        "2": "FM"
                    },
                    "Admin": 1,
                    "Offsite": [
                        "CM",
                        "DN",
                        "JT",
                        "ES",
                        "MI",
                        "TT"
                    ]
                }
            },
            "2": {
                "Thu": {
                    "Call": {
                        "1": "PM",
                        "2": "MC"
                    },
                    "Admin": 1,
                    "Requests": "PM 1st, MC 2nd",
                    "Offsite": [
                        "RR",
                        "DN",
                        "JT",
                        "ES",
                        "MI",
                        "TT"
                    ]
                }
            },
            "3": {
                "Fri": {
                    "Call": {
                        "1": "SL",
                        "2": "TI"
                    },
                    "Admin": 1,
                    "Offsite": [
                        "MA",
                        "DN",
                        "JT",
                        "ES",
                        "MI",
                        "TT"
                    ]
                }
            },
            "4": {
                "Sat AM": {
                    "Call": {
                        "1": "CA",
                        "2": "TI"
                    },
                    "Admin": 0,
                    "Requests": "RR, RK, off",
                    "Offsite": [
                        "MA",
                        "TI"
                    ]
                },
                "Sat PM": {
                    "Call": {
                        "1": "TI",
                        "2": "CA"
                    },
                    "Admin": 0,
                    "Offsite": [
                        "MA"
                    ]
                }
            },
            "5": {
                "Sun AM": {
                    "Call": {
                        "1": "SL",
                        "2": "TI"
                    },
                    "Admin": 0,
                    "Offsite": [
                        "MA"
                    ]
                },
                "Sun PM": {
                    "Call": {
                        "1": "CA",
                        "2": "TI"
                    },
                    "Admin": 0,
                    "Offsite": [
                        "MA"
                    ]
                }
            },
            "6": {
                "Mon": {
                    "Call": {
                        "1": "JJ",
                        "2": "RK"
                    },
                    "Admin": 1,
                    "Offsite": [
                        "RR",
                        "X",
                        "SL",
                        "JM",
                        "PM",
                        "DN",
                        "FM",
                        "SK"
                    ]
                }
            },
            "7": {
                "Tue": {
                    "Call": {
                        "1": "KK",
                        "2": "CC"
                    },
                    "Admin": 1,
                    "Offsite": [
                        "CM",
                        "JM",
                        "PM",
                        "DN",
                        "FM",
                        "SK"
                    ]
                }
            },
            "8": {
                "Wed": {
                    "Call": {
                        "1": "JT",
                        "2": "TI"
                    },
                    "Admin": 1,
                    "Offsite": [
                        "MA",
                        "JM",
                        "PM",
                        "DN",
                        "FM",
                        "SK"
                    ]
                }
            },
            "9": {
                "Thu": {
                    "Call": {
                        "1": "JJ",
                        "2": "CA"
                    },
                    "Admin": 1,
                    "Offsite": [
                        "RR",
                        "JM",
                        "PM",
                        "DN",
                        "FM",
                        "SK"
                    ]
                }
            },
            "10": {
                "Fri": {
                    "Call": {
                        "1": "KK",
                        "2": "ES"
                    },
                    "Admin": 1,
                    "Offsite": [
                        "CM",
                        "JM",
                        "PM",
                        "DN",
                        "FM",
                        "SK"
                    ]
                }
            },
            "11": {
                "Sat AM": {
                    "Call": {
                        "1": "TT",
                        "2": "ES"
                    },
                    "Admin": 0,
                    "Requests": "CA, RR, JJ off",
                    "Offsite": [
                        "CM",
                        "ES"
                    ]
                },
                "Sat PM": {
                    "Call": {
                        "1": "ES",
                        "2": "TT"
                    },
                    "Admin": 0,
                    "Offsite": [
                        "CM"
                    ]
                }
            },
            "12": {
                "Sun AM": {
                    "Call": {
                        "1": "KK",
                        "2": "ES"
                    },
                    "Admin": 0,
                    "Offsite": [
                        "CM"
                    ]
                },
                "Sun PM": {
                    "Call": {
                        "1": "TT",
                        "2": "ES"
                    },
                    "Admin": 0,
                    "Offsite": [
                        "CM"
                    ]
                }
            },
            "13": {
                "Mon": {
                    "Call": {
                        "1": "MC",
                        "2": "JT"
                    },
                    "Admin": 1,
                    "Requests": "JJ off",
                    "Offsite": [
                        "RR",
                        "X",
                        "PM",
                        "CA",
                        "SK",
                        "FM",
                        "DD",
                        "RK"
                    ]
                }
            },
            "14": {
                "Tue": {
                    "Call": {
                        "1": "SL",
                        "2": "DN"
                    },
                    "Admin": 1,
                    "Offsite": [
                        "MA",
                        "CA",
                        "SK",
                        "FM",
                        "DD",
                        "RK"
                    ]
                }
            },
            "15": {
                "Wed": {
                    "Call": {
                        "1": "ES",
                        "2": "KK"
                    },
                    "Admin": 1,
                    "Offsite": [
                        "CM",
                        "CA",
                        "SK",
                        "FM",
                        "DD",
                        "RK"
                    ]
                }
            },
            "16": {
                "Thu": {
                    "Call": {
                        "1": "JM",
                        "2": "TT"
                    },
                    "Admin": 1,
                    "Offsite": [
                        "RR",
                        "CA",
                        "SK",
                        "FM",
                        "DD",
                        "RK"
                    ]
                }
            },
            "17": {
                "Fri": {
                    "Call": {
                        "1": "SL",
                        "2": "JJ"
                    },
                    "Admin": 1,
                    "Offsite": [
                        "MA",
                        "CA",
                        "SK",
                        "FM",
                        "DD",
                        "RK"
                    ]
                }
            },
            "18": {
                "Sat AM": {
                    "Call": {
                        "1": "PM",
                        "2": "JJ"
                    },
                    "Admin": 0,
                    "Requests": "DN, JM off",
                    "Offsite": [
                        "MA",
                        "JJ"
                    ]
                },
                "Sat PM": {
                    "Call": {
                        "1": "JJ",
                        "2": "PM"
                    },
                    "Admin": 0,
                    "Offsite": [
                        "MA"
                    ]
                }
            },
            "19": {
                "Sun AM": {
                    "Call": {
                        "1": "SL",
                        "2": "JJ"
                    },
                    "Admin": 0,
                    "Offsite": [
                        "MA"
                    ]
                },
                "Sun PM": {
                    "Call": {
                        "1": "PM",
                        "2": "JJ"
                    },
                    "Admin": 0,
                    "Offsite": [
                        "MA"
                    ]
                }
            },
            "20": {
                "Mon": {
                    "Call": {
                        "1": "KK",
                        "2": "JM"
                    },
                    "Admin": 1,
                    "Offsite": [
                        "TI",
                        "DN",
                        "TI",
                        "X",
                        "PM",
                        "JT",
                        "RR",
                        "CC",
                        "CM",
                        "TT"
                    ]
                }
            },
            "21": {
                "Tue": {
                    "Call": {
                        "1": "ES",
                        "2": "SK"
                    },
                    "Admin": 1,
                    "Offsite": [
                        "DN",
                        "JT",
                        "RR",
                        "CC",
                        "CM",
                        "TT"
                    ]
                }
            },
            "22": {
                "Wed": {
                    "Call": {
                        "1": "MC",
                        "2": "JJ"
                    },
                    "Admin": 1,
                    "Offsite": [
                        "MA",
                        "JT",
                        "RR",
                        "CC",
                        "CM",
                        "TT"
                    ]
                }
            },
            "23": {
                "Thu": {
                    "Call": {
                        "1": "CA",
                        "2": "JM"
                    },
                    "Admin": 1,
                    "Offsite": [
                        "TI",
                        "JT",
                        "RR",
                        "CC",
                        "CM",
                        "TT"
                    ]
                }
            },
            "24": {
                "Fri": {
                    "Call": {
                        "1": "SK",
                        "2": "KK"
                    },
                    "Admin": 1,
                    "Offsite": [
                        "DN",
                        "JT",
                        "RR",
                        "CC",
                        "CM",
                        "TT"
                    ]
                }
            },
            "25": {
                "Sat AM": {
                    "Call": {
                        "1": "FM",
                        "2": "KK"
                    },
                    "Admin": 0,
                    "Requests": "JT, ES, off",
                    "Offsite": [
                        "DN",
                        "KK"
                    ]
                },
                "Sat PM": {
                    "Call": {
                        "1": "KK",
                        "2": "FM"
                    },
                    "Admin": 0,
                    "Offsite": [
                        "DN"
                    ]
                }
            },
            "26": {
                "Sun AM": {
                    "Call": {
                        "1": "SK",
                        "2": "KK"
                    },
                    "Admin": 0,
                    "Offsite": [
                        "DN"
                    ]
                },
                "Sun PM": {
                    "Call": {
                        "1": "FM",
                        "2": "KK"
                    },
                    "Admin": 0,
                    "Offsite": [
                        "DN"
                    ]
                }
            },
            "27": {
                "Mon": {
                    "Call": {
                        "1": "JT",
                        "2": "PM"
                    },
                    "Admin": 0,
                    "Offsite": [
                        "CM",
                        "RK",
                        "DN",
                        "X",
                        "SL",
                        "ES",
                        "TI",
                        "JM",
                        "MA",
                        "CA",
                        "MC"
                    ]
                }
            },
            "28": {
                "Tue": {
                    "Call": {
                        "1": "CC",
                        "2": "MI"
                    },
                    "Admin": 0,
                    "Offsite": [
                        "RK",
                        "ES",
                        "TI",
                        "JM",
                        "MA",
                        "CA",
                        "MC"
                    ]
                }
            },
            "29": {
                "Wed": {
                    "Call": {
                        "1": "SK",
                        "2": "TT"
                    },
                    "Admin": 0,
                    "Offsite": [
                        "DN",
                        "ES",
                        "TI",
                        "JM",
                        "MA",
                        "CA",
                        "MC"
                    ]
                }
            },
            "30": {
                "Thu": {
                    "Call": {
                        "1": "PM",
                        "2": "KK"
                    },
                    "Admin": 0,
                    "Offsite": [
                        "CM",
                        "ES",
                        "TI",
                        "JM",
                        "MA",
                        "CA",
                        "MC"
                    ]
                }
            },
            "31": {
                "Fri": {
                    "Call": {
                        "1": "JT",
                        "2": "MI"
                    },
                    "Admin": 0,
                    "Offsite": [
                        "RK",
                        "ES",
                        "TI",
                        "JM",
                        "MA",
                        "CA",
                        "MC"
                    ]
                }
            }
        },
        "Sep": {
            "1": {
                "Sat AM": {
                    "Call": {
                        "1": "RR",
                        "2": "MI"
                    },
                    "Admin": 0,
                    "Offsite": [
                        "RK",
                        "MI"
                    ]
                },
                "Sat PM": {
                    "Call": {
                        "1": "MI",
                        "2": "RR"
                    },
                    "Admin": 0,
                    "Offsite": [
                        "RK"
                    ]
                }
            },
            "2": {
                "Sun AM": {
                    "Call": {
                        "1": "JT",
                        "2": "MI"
                    },
                    "Admin": 0,
                    "Offsite": [
                        "RK"
                    ]
                },
                "Sun PM": {
                    "Call": {
                        "1": "RR",
                        "2": "MI"
                    },
                    "Admin": 0,
                    "Offsite": [
                        "RK"
                    ]
                }
            },
            "3": {
                "Mon AM": {
                    "Call": {
                        "1": "MI",
                        "2": "JT"
                    },
                    "Admin": 0,
                    "Offsite": [
                        "RK",
                        "RK",
                        "X",
                        "KK"
                    ]
                },
                "Mon PM": {
                    "Call": {
                        "1": "JT",
                        "2": "RR"
                    },
                    "Admin": 0,
                    "Offsite": [
                        "RK"
                    ]
                }
            },
            "4": {
                "Tue": {
                    "Call": {
                        "1": "SL",
                        "2": "SK"
                    },
                    "Admin": 1,
                    "Offsite": [
                        "MA",
                        "CC",
                        "TI",
                        "JM",
                        "MC",
                        "TT"
                    ]
                }
            },
            "5": {
                "Wed": {
                    "Call": {
                        "1": "PM",
                        "2": "DN"
                    },
                    "Admin": 1,
                    "Offsite": [
                        "CM",
                        "CC",
                        "JJ",
                        "JM",
                        "MC",
                        "TT"
                    ]
                }
            },
            "6": {
                "Thu": {
                    "Call": {
                        "1": "FM",
                        "2": "MI"
                    },
                    "Admin": 1,
                    "Offsite": [
                        "RK",
                        "CC",
                        "JJ",
                        "JM",
                        "MC",
                        "TT"
                    ]
                }
            },
            "7": {
                "Fri": {
                    "Call": {
                        "1": "ES",
                        "2": "CA"
                    },
                    "Admin": 1,
                    "Offsite": [
                        "MA",
                        "CC",
                        "JJ",
                        "JM",
                        "MC",
                        "TT"
                    ]
                }
            },
            "8": {
                "Sat AM": {
                    "Call": {
                        "1": "SL",
                        "2": "CA"
                    },
                    "Admin": 0,
                    "Offsite": [
                        "MA",
                        "CA"
                    ]
                },
                "Sat PM": {
                    "Call": {
                        "1": "CA",
                        "2": "SL"
                    },
                    "Admin": 0,
                    "Offsite": [
                        "MA"
                    ]
                }
            },
            "9": {
                "Sun AM": {
                    "Call": {
                        "1": "ES",
                        "2": "CA"
                    },
                    "Admin": 0,
                    "Offsite": [
                        "MA"
                    ]
                },
                "Sun PM": {
                    "Call": {
                        "1": "SL",
                        "2": "CA"
                    },
                    "Admin": 0,
                    "Offsite": [
                        "MA"
                    ]
                }
            },
            "10": {
                "Mon": {
                    "Call": {
                        "1": "RK",
                        "2": "FM"
                    },
                    "Admin": 1,
                    "Offsite": [
                        "JJ",
                        "JJ",
                        "MI",
                        "SK",
                        "JM",
                        "KK",
                        "PM",
                        "JT",
                        "CM"
                    ]
                }
            },
            "11": {
                "Tue": {
                    "Call": {
                        "1": "TT",
                        "2": "CC"
                    },
                    "Admin": 1,
                    "Offsite": [
                        "RR",
                        "JM",
                        "KK",
                        "PM",
                        "JT",
                        "CM"
                    ]
                }
            },
            "12": {
                "Wed": {
                    "Call": {
                        "1": "ES",
                        "2": "CA"
                    },
                    "Admin": 1,
                    "Offsite": [
                        "MA",
                        "JM",
                        "KK",
                        "PM",
                        "JT",
                        "CM"
                    ]
                }
            },
            "13": {
                "Thu": {
                    "Call": {
                        "1": "FM",
                        "2": "SL"
                    },
                    "Admin": 1,
                    "Offsite": [
                        "MI",
                        "JM",
                        "KK",
                        "PM",
                        "JT",
                        "CM"
                    ]
                }
            },
            "14": {
                "Fri": {
                    "Call": {
                        "1": "TT",
                        "2": "CC"
                    },
                    "Admin": 1,
                    "Offsite": [
                        "JJ",
                        "JM",
                        "KK",
                        "PM",
                        "JT",
                        "CM"
                    ]
                }
            },
            "15": {
                "Sat AM": {
                    "Call": {
                        "1": "TI",
                        "2": "CC"
                    },
                    "Admin": 0,
                    "Offsite": [
                        "JJ",
                        "CC"
                    ]
                },
                "Sat PM": {
                    "Call": {
                        "1": "CC",
                        "2": "TI"
                    },
                    "Admin": 0,
                    "Offsite": [
                        "JJ"
                    ]
                }
            },
            "16": {
                "Sun AM": {
                    "Call": {
                        "1": "TT",
                        "2": "CC"
                    },
                    "Admin": 0,
                    "Offsite": [
                        "JJ"
                    ]
                },
                "Sun PM": {
                    "Call": {
                        "1": "TI",
                        "2": "CC"
                    },
                    "Admin": 0,
                    "Offsite": [
                        "JJ"
                    ]
                }
            },
            "17": {
                "Mon": {
                    "Call": {
                        "1": "JM",
                        "2": "ES"
                    },
                    "Admin": 0,
                    "Offsite": [
                        "CM",
                        "X",
                        "DN",
                        "RK",
                        "SL",
                        "KK",
                        "PM",
                        "FM",
                        "SK"
                    ]
                }
            },
            "18": {
                "Tue": {
                    "Call": {
                        "1": "MC",
                        "2": "MI"
                    },
                    "Admin": 0,
                    "Offsite": [
                        "RR",
                        "RK",
                        "SL",
                        "KK",
                        "PM",
                        "FM",
                        "SK"
                    ]
                }
            },
            "19": {
                "Wed": {
                    "Call": {
                        "1": "CA",
                        "2": "TI"
                    },
                    "Admin": 0,
                    "Offsite": [
                        "MA",
                        "RK",
                        "SL",
                        "KK",
                        "PM",
                        "FM",
                        "SK"
                    ]
                }
            },
            "20": {
                "Thu": {
                    "Call": {
                        "1": "ES",
                        "2": "JT"
                    },
                    "Admin": 0,
                    "Offsite": [
                        "CM",
                        "CC",
                        "SL",
                        "KK",
                        "PM",
                        "FM",
                        "SK"
                    ]
                }
            },
            "21": {
                "Fri": {
                    "Call": {
                        "1": "MC",
                        "2": "JM"
                    },
                    "Admin": 0,
                    "Offsite": [
                        "RR",
                        "CC",
                        "SL",
                        "KK",
                        "PM",
                        "FM",
                        "SK"
                    ]
                }
            },
            "22": {
                "Sat AM": {
                    "Call": {
                        "1": "RK",
                        "2": "JM"
                    },
                    "Admin": 0,
                    "Offsite": [
                        "RR",
                        "JM"
                    ]
                },
                "Sat PM": {
                    "Call": {
                        "1": "JM",
                        "2": "RK"
                    },
                    "Admin": 0,
                    "Offsite": [
                        "RR"
                    ]
                }
            },
            "23": {
                "Sun AM": {
                    "Call": {
                        "1": "MC",
                        "2": "JM"
                    },
                    "Admin": 0,
                    "Offsite": [
                        "RR"
                    ]
                },
                "Sun PM": {
                    "Call": {
                        "1": "RK",
                        "2": "JM"
                    },
                    "Admin": 0,
                    "Offsite": [
                        "RR"
                    ]
                }
            },
            "24": {
                "Mon": {
                    "Call": {
                        "1": "SK",
                        "2": "TT"
                    },
                    "Admin": 1,
                    "Offsite": [
                        "CM",
                        "CA",
                        "X",
                        "PM",
                        "TI",
                        "DD",
                        "SL",
                        "DN",
                        "KK"
                    ]
                }
            },
            "25": {
                "Tue": {
                    "Call": {
                        "1": "MI",
                        "2": "ES"
                    },
                    "Admin": 1,
                    "Offsite": [
                        "CA",
                        "TI",
                        "DD",
                        "SL",
                        "DN",
                        "KK"
                    ]
                }
            },
            "26": {
                "Wed": {
                    "Call": {
                        "1": "JJ",
                        "2": "MC"
                    },
                    "Admin": 1,
                    "Offsite": [
                        "CM",
                        "TI",
                        "DD",
                        "SL",
                        "DN",
                        "KK"
                    ]
                }
            },
            "27": {
                "Thu": {
                    "Call": {
                        "1": "CC",
                        "2": "MA"
                    },
                    "Admin": 1,
                    "Requests": "CC on",
                    "Offsite": [
                        "RR",
                        "TI",
                        "DD",
                        "SL",
                        "DN",
                        "KK"
                    ]
                }
            },
            "28": {
                "Fri": {
                    "Call": {
                        "1": "SK",
                        "2": "FM"
                    },
                    "Admin": 1,
                    "Offsite": [
                        "CM",
                        "TI",
                        "DD",
                        "SL",
                        "DN",
                        "KK"
                    ]
                }
            },
            "29": {
                "Sat AM": {
                    "Call": {
                        "1": "ES",
                        "2": "FM"
                    },
                    "Admin": 0,
                    "Offsite": [
                        "CM",
                        "FM"
                    ]
                },
                "Sat PM": {
                    "Call": {
                        "1": "FM",
                        "2": "ES"
                    },
                    "Admin": 0,
                    "Offsite": [
                        "CM"
                    ]
                }
            },
            "30": {
                "Sun AM": {
                    "Call": {
                        "1": "SK",
                        "2": "FM"
                    },
                    "Admin": 0,
                    "Offsite": [
                        "CM"
                    ]
                },
                "Sun PM": {
                    "Call": {
                        "1": "ES",
                        "2": "FM"
                    },
                    "Admin": 0,
                    "Offsite": [
                        "CM"
                    ]
                }
            }
        }
    }
}