{
    "2019": {
        "Dec": {
            "30": {
                "Mon": {
                    "Call": {
                        "1": "SK",
                        "2": "RR"
                    },
                    "Admin": 1,
                    "Offsite": [
                        "MA",
                        "TT",
                        "X",
                        "KK",
                        "RK",
                        "JT",
                        "DN",
                        "CC",
                        "MC",
                        "PM"
                    ]
                }
            },
            "31": {
                "Tue": {
                    "Call": {
                        "1": "KC",
                        "2": "ES"
                    },
                    "Admin": 1,
                    "Offsite": [
                        "TT",
                        "RK",
                        "JT",
                        "DN",
                        "CC",
                        "MC",
                        "PM"
                    ]
                }
            }
        }
    },
    "2020": {
        "Jan": {
            "1": {
                "Wed": {
                    "Call": {
                        "1": "ES",
                        "2": "KC"
                    },
                    "Admin": 1,
                    "Offsite": [
                        "TT",
                        "JT",
                        "DN",
                        "CC",
                        "MC",
                        "PM"
                    ]
                }
            },
            "2": {
                "Thu": {
                    "Call": {
                        "1": "TI",
                        "2": "MI"
                    },
                    "Admin": 1,
                    "Requests": "MI 2nd",
                    "Offsite": [
                        "JJ",
                        "RK",
                        "JT",
                        "DN",
                        "CC",
                        "MC",
                        "PM"
                    ]
                }
            },
            "3": {
                "Fri": {
                    "Call": {
                        "1": "RR",
                        "2": "FM"
                    },
                    "Admin": 1,
                    "Offsite": [
                        "MA",
                        "RK",
                        "JT",
                        "DN",
                        "CC",
                        "MC",
                        "PM"
                    ]
                }
            },
            "4": {
                "Sat AM": {
                    "Call": {
                        "1": "SK",
                        "2": "FM"
                    },
                    "Admin": 0,
                    "Offsite": [
                        "MA",
                        "FM"
                    ]
                },
                "Sat PM": {
                    "Call": {
                        "1": "FM",
                        "2": "SK"
                    },
                    "Admin": 0,
                    "Offsite": [
                        "MA"
                    ]
                }
            },
            "5": {
                "Sun AM": {
                    "Call": {
                        "1": "RR",
                        "2": "FM"
                    },
                    "Admin": 0,
                    "Offsite": [
                        "MA"
                    ]
                },
                "Sun PM": {
                    "Call": {
                        "1": "SK",
                        "2": "FM"
                    },
                    "Admin": 0,
                    "Offsite": [
                        "MA"
                    ]
                }
            },
            "6": {
                "Mon": {
                    "Call": {
                        "1": "CA",
                        "2": "CM"
                    },
                    "Admin": 1,
                    "Offsite": [
                        "KC",
                        "JM",
                        "X",
                        "PM",
                        "MC",
                        "JJ",
                        "MI",
                        "TI",
                        "KK",
                        "RK"
                    ]
                }
            },
            "7": {
                "Tue": {
                    "Call": {
                        "1": "DN",
                        "2": "SL"
                    },
                    "Admin": 1,
                    "Offsite": [
                        "JM",
                        "MC",
                        "JJ",
                        "MI",
                        "TI",
                        "KK",
                        "RK"
                    ]
                }
            },
            "8": {
                "Wed": {
                    "Call": {
                        "1": "RR",
                        "2": "SK"
                    },
                    "Admin": 1,
                    "Offsite": [
                        "MA",
                        "MC",
                        "JJ",
                        "MI",
                        "TI",
                        "KK",
                        "RK"
                    ]
                }
            },
            "9": {
                "Thu": {
                    "Call": {
                        "1": "ES",
                        "2": "TT"
                    },
                    "Admin": 1,
                    "Requests": "ES 1st",
                    "Offsite": [
                        "KC",
                        "MC",
                        "JJ",
                        "MI",
                        "TI",
                        "KK",
                        "RK"
                    ]
                }
            },
            "10": {
                "Fri": {
                    "Call": {
                        "1": "SL",
                        "2": "CM"
                    },
                    "Admin": 1,
                    "Offsite": [
                        "JM",
                        "MC",
                        "JJ",
                        "MI",
                        "TI",
                        "KK",
                        "RK"
                    ]
                }
            },
            "11": {
                "Sat AM": {
                    "Call": {
                        "1": "JT",
                        "2": "CM"
                    },
                    "Admin": 0,
                    "Requests": "DN off",
                    "Offsite": [
                        "JM",
                        "CM"
                    ]
                },
                "Sat PM": {
                    "Call": {
                        "1": "CM",
                        "2": "JT"
                    },
                    "Admin": 0,
                    "Offsite": [
                        "JM"
                    ]
                }
            },
            "12": {
                "Sun AM": {
                    "Call": {
                        "1": "SL",
                        "2": "CM"
                    },
                    "Admin": 0,
                    "Offsite": [
                        "JM"
                    ]
                },
                "Sun PM": {
                    "Call": {
                        "1": "JT",
                        "2": "CM"
                    },
                    "Admin": 0,
                    "Offsite": [
                        "JM"
                    ]
                }
            },
            "13": {
                "Mon": {
                    "Call": {
                        "1": "FM",
                        "2": "PM"
                    },
                    "Admin": 1,
                    "Offsite": [
                        "MA",
                        "MC",
                        "X",
                        "SK",
                        "RR",
                        "TT",
                        "MI",
                        "ES",
                        "KC",
                        "KK"
                    ]
                }
            },
            "14": {
                "Tue": {
                    "Call": {
                        "1": "CC",
                        "2": "RK"
                    },
                    "Admin": 1,
                    "Offsite": [
                        "JJ",
                        "RR",
                        "TT",
                        "MI",
                        "ES",
                        "KC",
                        "KK"
                    ]
                }
            },
            "15": {
                "Wed": {
                    "Call": {
                        "1": "JT",
                        "2": "CM"
                    },
                    "Admin": 1,
                    "Offsite": [
                        "MC",
                        "RR",
                        "TT",
                        "MI",
                        "ES",
                        "KC",
                        "KK"
                    ]
                }
            },
            "16": {
                "Thu": {
                    "Call": {
                        "1": "SL",
                        "2": "JM"
                    },
                    "Admin": 1,
                    "Offsite": [
                        "MA",
                        "RR",
                        "TT",
                        "MI",
                        "ES",
                        "KC",
                        "KK"
                    ]
                }
            },
            "17": {
                "Fri": {
                    "Call": {
                        "1": "RK",
                        "2": "PM"
                    },
                    "Admin": 1,
                    "Offsite": [
                        "JJ",
                        "RR",
                        "TT",
                        "MI",
                        "ES",
                        "KC",
                        "KK"
                    ]
                }
            },
            "18": {
                "Sat AM": {
                    "Call": {
                        "1": "DN",
                        "2": "PM"
                    },
                    "Admin": 0,
                    "Requests": "PM on, FM/SK off",
                    "Offsite": [
                        "JJ",
                        "PM"
                    ]
                },
                "Sat PM": {
                    "Call": {
                        "1": "PM",
                        "2": "DN"
                    },
                    "Admin": 0,
                    "Offsite": [
                        "JJ"
                    ]
                }
            },
            "19": {
                "Sun AM": {
                    "Call": {
                        "1": "RK",
                        "2": "PM"
                    },
                    "Admin": 0,
                    "Offsite": [
                        "JJ"
                    ]
                },
                "Sun PM": {
                    "Call": {
                        "1": "DN",
                        "2": "PM"
                    },
                    "Admin": 0,
                    "Offsite": [
                        "JJ"
                    ]
                }
            },
            "20": {
                "Mon": {
                    "Call": {
                        "1": "SK",
                        "2": "KK"
                    },
                    "Admin": 1,
                    "Offsite": [
                        "MC",
                        "MC",
                        "X",
                        "RR",
                        "JM",
                        "SL",
                        "CC",
                        "MA",
                        "TI",
                        "CM"
                    ]
                }
            },
            "21": {
                "Tue": {
                    "Call": {
                        "1": "MI",
                        "2": "JT"
                    },
                    "Admin": 1,
                    "Offsite": [
                        "KC",
                        "JM",
                        "SL",
                        "CC",
                        "MA",
                        "TI",
                        "CM"
                    ]
                }
            },
            "22": {
                "Wed": {
                    "Call": {
                        "1": "FM",
                        "2": "PM"
                    },
                    "Admin": 1,
                    "Offsite": [
                        "JJ",
                        "JM",
                        "SL",
                        "CC",
                        "MA",
                        "TI",
                        "CM"
                    ]
                }
            },
            "23": {
                "Thu": {
                    "Call": {
                        "1": "DN",
                        "2": "CA"
                    },
                    "Admin": 1,
                    "Offsite": [
                        "MC",
                        "JM",
                        "SL",
                        "CC",
                        "MA",
                        "TI",
                        "CM"
                    ]
                }
            },
            "24": {
                "Fri": {
                    "Call": {
                        "1": "MI",
                        "2": "KK"
                    },
                    "Admin": 1,
                    "Offsite": [
                        "KC",
                        "JM",
                        "SL",
                        "CC",
                        "MA",
                        "TI",
                        "CM"
                    ]
                }
            },
            "25": {
                "Sat AM": {
                    "Call": {
                        "1": "JT",
                        "2": "KK"
                    },
                    "Admin": 0,
                    "Offsite": [
                        "KC",
                        "KK"
                    ]
                },
                "Sat PM": {
                    "Call": {
                        "1": "KK",
                        "2": "JT"
                    },
                    "Admin": 0,
                    "Offsite": [
                        "KC"
                    ]
                }
            },
            "26": {
                "Sun AM": {
                    "Call": {
                        "1": "MI",
                        "2": "KK"
                    },
                    "Admin": 0,
                    "Offsite": [
                        "KC"
                    ]
                },
                "Sun PM": {
                    "Call": {
                        "1": "JT",
                        "2": "KK"
                    },
                    "Admin": 0,
                    "Offsite": [
                        "KC"
                    ]
                }
            },
            "27": {
                "Mon": {
                    "Call": {
                        "1": "FM",
                        "2": "CC"
                    },
                    "Admin": 1,
                    "Offsite": [
                        "CM",
                        "CM",
                        "TI",
                        "SK",
                        "ES",
                        "SL",
                        "DD",
                        "DN",
                        "CA",
                        "PM"
                    ]
                }
            },
            "28": {
                "Tue": {
                    "Call": {
                        "1": "RR",
                        "2": "RK"
                    },
                    "Admin": 1,
                    "Offsite": [
                        "TI",
                        "MA@MCH",
                        "ES",
                        "SL",
                        "DD",
                        "DN",
                        "CA",
                        "PM"
                    ]
                }
            },
            "29": {
                "Wed": {
                    "Call": {
                        "1": "JT",
                        "2": "MI"
                    },
                    "Admin": 1,
                    "Offsite": [
                        "JJ",
                        "ES",
                        "SL",
                        "DD",
                        "DN",
                        "CA",
                        "PM"
                    ]
                }
            },
            "30": {
                "Thu": {
                    "Call": {
                        "1": "KK",
                        "2": "FM"
                    },
                    "Admin": 1,
                    "Requests": "KC on",
                    "Offsite": [
                        "KC",
                        "ES",
                        "SL",
                        "DD",
                        "DN",
                        "CA",
                        "PM"
                    ]
                }
            },
            "31": {
                "Fri": {
                    "Call": {
                        "1": "CC",
                        "2": "MC"
                    },
                    "Admin": 1,
                    "Offsite": [
                        "CM",
                        "ES",
                        "SL",
                        "DD",
                        "DN",
                        "CA",
                        "PM"
                    ]
                }
            }
        },
        "Feb": {
            "1": {
                "Sat AM": {
                    "Call": {
                        "1": "JM",
                        "2": "MC"
                    },
                    "Admin": 0,
                    "Requests": "TI, RR off",
                    "Offsite": [
                        "CM",
                        "MC"
                    ]
                },
                "Sat PM": {
                    "Call": {
                        "1": "MC",
                        "2": "JM"
                    },
                    "Admin": 0,
                    "Requests": "FM/SK no 1st call",
                    "Offsite": [
                        "CM"
                    ]
                }
            },
            "2": {
                "Sun AM": {
                    "Call": {
                        "1": "CC",
                        "2": "MC"
                    },
                    "Admin": 0,
                    "Offsite": [
                        "CM"
                    ]
                },
                "Sun PM": {
                    "Call": {
                        "1": "JM",
                        "2": "MC"
                    },
                    "Admin": 0,
                    "Offsite": [
                        "CM"
                    ]
                }
            },
            "3": {
                "Mon": {
                    "Call": {
                        "1": "SK",
                        "2": "SL"
                    },
                    "Admin": 1,
                    "Requests": "CM off",
                    "Offsite": [
                        "ES",
                        "CM",
                        "ES",
                        "DN",
                        "RR",
                        "JT",
                        "JJ",
                        "KC",
                        "PM",
                        "RK",
                        "KK"
                    ]
                }
            },
            "4": {
                "Tue": {
                    "Call": {
                        "1": "MI",
                        "2": "TT"
                    },
                    "Admin": 1,
                    "Offsite": [
                        "DN",
                        "JT",
                        "JJ",
                        "KC",
                        "PM",
                        "RK",
                        "KK"
                    ]
                }
            },
            "5": {
                "Wed": {
                    "Call": {
                        "1": "CC",
                        "2": "CA"
                    },
                    "Admin": 1,
                    "Offsite": [
                        "MA",
                        "JT",
                        "JJ",
                        "KC",
                        "PM",
                        "RK",
                        "KK"
                    ]
                }
            },
            "6": {
                "Thu": {
                    "Call": {
                        "1": "JM",
                        "2": "TI"
                    },
                    "Admin": 1,
                    "Offsite": [
                        "CM",
                        "JT",
                        "JJ",
                        "KC",
                        "PM",
                        "RK",
                        "KK"
                    ]
                }
            },
            "7": {
                "Fri": {
                    "Call": {
                        "1": "FM",
                        "2": "SK"
                    },
                    "Admin": 1,
                    "Offsite": [
                        "ES",
                        "JT",
                        "JJ",
                        "KC",
                        "PM",
                        "RK",
                        "KK"
                    ]
                }
            },
            "8": {
                "Sat AM": {
                    "Call": {
                        "1": "SL",
                        "2": "SK"
                    },
                    "Admin": 0,
                    "Requests": "DN, TT off",
                    "Offsite": [
                        "ES",
                        "SK"
                    ]
                },
                "Sat PM": {
                    "Call": {
                        "1": "SK",
                        "2": "SL"
                    },
                    "Admin": 0,
                    "Offsite": [
                        "ES"
                    ]
                }
            },
            "9": {
                "Sun AM": {
                    "Call": {
                        "1": "FM",
                        "2": "SK"
                    },
                    "Admin": 0,
                    "Offsite": [
                        "ES"
                    ]
                },
                "Sun PM": {
                    "Call": {
                        "1": "SL",
                        "2": "SK"
                    },
                    "Admin": 0,
                    "Offsite": [
                        "ES"
                    ]
                }
            },
            "10": {
                "Mon": {
                    "Call": {
                        "1": "PM",
                        "2": "CM"
                    },
                    "Admin": 1,
                    "Offsite": [
                        "MA",
                        "X",
                        "SK",
                        "DD",
                        "TI",
                        "RR",
                        "JM",
                        "MC",
                        "RK"
                    ]
                }
            },
            "11": {
                "Tue": {
                    "Call": {
                        "1": "CA",
                        "2": "KK"
                    },
                    "Admin": 1,
                    "Offsite": [
                        "JJ",
                        "DD",
                        "TI",
                        "RR",
                        "JM",
                        "MC",
                        "RK"
                    ]
                }
            },
            "12": {
                "Wed": {
                    "Call": {
                        "1": "DN",
                        "2": "FM"
                    },
                    "Admin": 1,
                    "Offsite": [
                        "KC",
                        "DD",
                        "TI",
                        "RR",
                        "JM",
                        "MC",
                        "RK"
                    ]
                }
            },
            "13": {
                "Thu": {
                    "Call": {
                        "1": "TT",
                        "2": "CC"
                    },
                    "Admin": 1,
                    "Requests": "CC 2nd",
                    "Offsite": [
                        "MA",
                        "DD",
                        "TI",
                        "RR",
                        "JM",
                        "MC",
                        "RK"
                    ]
                }
            },
            "14": {
                "Fri": {
                    "Call": {
                        "1": "PM",
                        "2": "MI"
                    },
                    "Admin": 1,
                    "Offsite": [
                        "JJ",
                        "DD",
                        "TI",
                        "RR",
                        "JM",
                        "MC",
                        "RK"
                    ]
                }
            },
            "15": {
                "Sat AM": {
                    "Call": {
                        "1": "CA",
                        "2": "MI"
                    },
                    "Admin": 0,
                    "Requests": "PM, CA on, SK/FM off",
                    "Offsite": [
                        "JJ",
                        "MI"
                    ]
                },
                "Sat PM": {
                    "Call": {
                        "1": "MI",
                        "2": "CA"
                    },
                    "Admin": 0,
                    "Offsite": [
                        "JJ"
                    ]
                }
            },
            "16": {
                "Sun AM": {
                    "Call": {
                        "1": "PM",
                        "2": "MI"
                    },
                    "Admin": 0,
                    "Offsite": [
                        "JJ"
                    ]
                },
                "Sun PM": {
                    "Call": {
                        "1": "CA",
                        "2": "MI"
                    },
                    "Admin": 0,
                    "Offsite": [
                        "JJ"
                    ]
                }
            },
            "17": {
                "Mon": {
                    "Call": {
                        "1": "FM",
                        "2": "MC"
                    },
                    "Admin": 1,
                    "Offsite": [
                        "KC",
                        "X",
                        "KK",
                        "ES",
                        "JM",
                        "TI",
                        "TT",
                        "RK",
                        "DN"
                    ]
                }
            },
            "18": {
                "Tue": {
                    "Call": {
                        "1": "SL",
                        "2": "RR"
                    },
                    "Admin": 1,
                    "Offsite": [
                        "MA",
                        "ES",
                        "JM",
                        "TI",
                        "TT",
                        "RK",
                        "DN"
                    ]
                }
            },
            "19": {
                "Wed": {
                    "Call": {
                        "1": "PM",
                        "2": "SK"
                    },
                    "Admin": 1,
                    "Offsite": [
                        "JJ",
                        "ES",
                        "JM",
                        "TI",
                        "TT",
                        "RK",
                        "DN"
                    ]
                }
            },
            "20": {
                "Thu": {
                    "Call": {
                        "1": "MI",
                        "2": "JT"
                    },
                    "Admin": 1,
                    "Requests": "MI 1st",
                    "Offsite": [
                        "KC",
                        "ES",
                        "JM",
                        "TI",
                        "TT",
                        "RK",
                        "DN"
                    ]
                }
            },
            "21": {
                "Fri": {
                    "Call": {
                        "1": "RR",
                        "2": "MC"
                    },
                    "Admin": 1,
                    "Offsite": [
                        "MA",
                        "ES",
                        "JM",
                        "TI",
                        "TT",
                        "RK",
                        "DN"
                    ]
                }
            },
            "22": {
                "Sat AM": {
                    "Call": {
                        "1": "CC",
                        "2": "MC"
                    },
                    "Admin": 0,
                    "Offsite": [
                        "MA",
                        "MC"
                    ]
                },
                "Sat PM": {
                    "Call": {
                        "1": "MC",
                        "2": "CC"
                    },
                    "Admin": 0,
                    "Offsite": [
                        "MA"
                    ]
                }
            },
            "23": {
                "Sun AM": {
                    "Call": {
                        "1": "RR",
                        "2": "MC"
                    },
                    "Admin": 0,
                    "Offsite": [
                        "MA"
                    ]
                },
                "Sun PM": {
                    "Call": {
                        "1": "CC",
                        "2": "MC"
                    },
                    "Admin": 0,
                    "Offsite": [
                        "MA"
                    ]
                }
            },
            "24": {
                "Mon": {
                    "Call": {
                        "1": "JM",
                        "2": "RK"
                    },
                    "Admin": 1,
                    "Offsite": [
                        "JJ",
                        "X",
                        "SK",
                        "CA",
                        "ES",
                        "KK",
                        "MI",
                        "JT",
                        "CM"
                    ]
                }
            },
            "25": {
                "Tue": {
                    "Call": {
                        "1": "TT",
                        "2": "FM"
                    },
                    "Admin": 1,
                    "Offsite": [
                        "KC",
                        "CA",
                        "ES",
                        "KK",
                        "MI",
                        "JT",
                        "CM"
                    ]
                }
            },
            "26": {
                "Wed": {
                    "Call": {
                        "1": "SL",
                        "2": "DN"
                    },
                    "Admin": 1,
                    "Requests": "SL on",
                    "Offsite": [
                        "MA",
                        "CA",
                        "ES",
                        "KK",
                        "MI",
                        "JT",
                        "CM"
                    ]
                }
            },
            "27": {
                "Thu": {
                    "Call": {
                        "1": "PM",
                        "2": "RR"
                    },
                    "Admin": 1,
                    "Offsite": [
                        "JJ",
                        "CA",
                        "ES",
                        "KK",
                        "MI",
                        "JT",
                        "CM"
                    ]
                }
            },
            "28": {
                "Fri": {
                    "Call": {
                        "1": "TT",
                        "2": "JM"
                    },
                    "Admin": 1,
                    "Offsite": [
                        "KC",
                        "CA",
                        "ES",
                        "KK",
                        "MI",
                        "JT",
                        "CM"
                    ]
                }
            },
            "29": {
                "Sat AM": {
                    "Call": {
                        "1": "TI",
                        "2": "JM"
                    },
                    "Admin": 0,
                    "Requests": "RR off",
                    "Offsite": [
                        "KC",
                        "JM"
                    ]
                },
                "Sat PM": {
                    "Call": {
                        "1": "JM",
                        "2": "TI"
                    },
                    "Admin": 0,
                    "Offsite": [
                        "KC"
                    ]
                }
            }
        },
        "Mar": {
            "1": {
                "Sun AM": {
                    "Call": {
                        "1": "TT",
                        "2": "JM"
                    },
                    "Admin": 0,
                    "Offsite": [
                        "KC"
                    ]
                },
                "Sun PM": {
                    "Call": {
                        "1": "TI",
                        "2": "JM"
                    },
                    "Admin": 0,
                    "Offsite": [
                        "KC"
                    ]
                }
            },
            "2": {
                "Mon": {
                    "Call": {
                        "1": "RR",
                        "2": "SK"
                    },
                    "Admin": 2,
                    "Requests": "JT off",
                    "Offsite": [
                        "JJ",
                        "ES",
                        "X",
                        "SL",
                        "DN",
                        "CM",
                        "MA",
                        "KK",
                        "PM"
                    ]
                }
            },
            "3": {
                "Tue": {
                    "Call": {
                        "1": "CC",
                        "2": "MC"
                    },
                    "Admin": 2,
                    "Offsite": [
                        "ES",
                        "DN",
                        "CM",
                        "MA",
                        "KK",
                        "PM"
                    ]
                }
            },
            "4": {
                "Wed": {
                    "Call": {
                        "1": "JT",
                        "2": "TI"
                    },
                    "Admin": 2,
                    "Offsite": [
                        "KC",
                        "DN",
                        "CM",
                        "MA",
                        "KK",
                        "PM"
                    ]
                }
            },
            "5": {
                "Thu": {
                    "Call": {
                        "1": "RK",
                        "2": "JM"
                    },
                    "Admin": 2,
                    "Offsite": [
                        "JJ",
                        "DN",
                        "CM",
                        "MA",
                        "KK",
                        "PM"
                    ]
                }
            },
            "6": {
                "Fri": {
                    "Call": {
                        "1": "SK",
                        "2": "FM"
                    },
                    "Admin": 2,
                    "Offsite": [
                        "ES",
                        "KK",
                        "CM",
                        "MA",
                        "DN",
                        "PM"
                    ]
                }
            },
            "7": {
                "Sat AM": {
                    "Call": {
                        "1": "CA",
                        "2": "FM"
                    },
                    "Admin": 0,
                    "Requests": "CA on",
                    "Offsite": [
                        "ES",
                        "FM"
                    ]
                },
                "Sat PM": {
                    "Call": {
                        "1": "FM",
                        "2": "CA"
                    },
                    "Admin": 0,
                    "Offsite": [
                        "ES"
                    ]
                }
            },
            "8": {
                "Sun AM": {
                    "Call": {
                        "1": "SK",
                        "2": "FM"
                    },
                    "Admin": 0,
                    "Offsite": [
                        "ES"
                    ]
                },
                "Sun PM": {
                    "Call": {
                        "1": "CA",
                        "2": "FM"
                    },
                    "Admin": 0,
                    "Offsite": [
                        "ES"
                    ]
                }
            },
            "9": {
                "Mon": {
                    "Call": {
                        "1": "MC",
                        "2": "SL"
                    },
                    "Admin": 3,
                    "Offsite": [
                        "MA",
                        "X",
                        "KK",
                        "JM",
                        "DD",
                        "PM",
                        "CM"
                    ]
                }
            },
            "10": {
                "Tue": {
                    "Call": {
                        "1": "RR",
                        "2": "TI"
                    },
                    "Admin": 3,
                    "Offsite": [
                        "JJ",
                        "JM",
                        "DD",
                        "PM",
                        "CM"
                    ]
                }
            },
            "11": {
                "Wed": {
                    "Call": {
                        "1": "CA",
                        "2": "TT"
                    },
                    "Admin": 3,
                    "Offsite": [
                        "KC",
                        "JM",
                        "DD",
                        "PM",
                        "CM"
                    ]
                }
            },
            "12": {
                "Thu": {
                    "Call": {
                        "1": "SK",
                        "2": "CC"
                    },
                    "Admin": 3,
                    "Requests": "CC 2nd",
                    "Offsite": [
                        "MA",
                        "JM",
                        "DD",
                        "PM",
                        "RK"
                    ]
                }
            },
            "13": {
                "Fri": {
                    "Call": {
                        "1": "JT",
                        "2": "TI"
                    },
                    "Admin": 3,
                    "Offsite": [
                        "JJ",
                        "JM",
                        "DD",
                        "PM",
                        "RK"
                    ]
                }
            },
            "14": {
                "Sat AM": {
                    "Call": {
                        "1": "SL",
                        "2": "TI"
                    },
                    "Admin": 0,
                    "Offsite": [
                        "JJ",
                        "TI"
                    ]
                },
                "Sat PM": {
                    "Call": {
                        "1": "TI",
                        "2": "SL"
                    },
                    "Admin": 0,
                    "Offsite": [
                        "JJ"
                    ]
                }
            },
            "15": {
                "Sun AM": {
                    "Call": {
                        "1": "JT",
                        "2": "TI"
                    },
                    "Admin": 0,
                    "Offsite": [
                        "JJ"
                    ]
                },
                "Sun PM": {
                    "Call": {
                        "1": "SL",
                        "2": "TI"
                    },
                    "Admin": 0,
                    "Offsite": [
                        "JJ"
                    ]
                }
            },
            "16": {
                "Mon": {
                    "Call": {
                        "1": "RK",
                        "2": "CA"
                    },
                    "Admin": 0,
                    "Offsite": [
                        "CM",
                        "CM",
                        "X",
                        "RR",
                        "PM",
                        "FM",
                        "SK",
                        "CC",
                        "KC",
                        "TT",
                        "KK"
                    ]
                }
            },
            "17": {
                "Tue": {
                    "Call": {
                        "1": "MI",
                        "2": "DN"
                    },
                    "Admin": 0,
                    "Offsite": [
                        "MA",
                        "PM",
                        "FM",
                        "SK",
                        "CC",
                        "KC",
                        "TT",
                        "KK"
                    ]
                }
            },
            "18": {
                "Wed": {
                    "Call": {
                        "1": "TI",
                        "2": "JM"
                    },
                    "Admin": 0,
                    "Offsite": [
                        "JJ",
                        "PM",
                        "FM",
                        "SK",
                        "CC",
                        "KC",
                        "TT",
                        "KK"
                    ]
                }
            },
            "19": {
                "Thu": {
                    "Call": {
                        "1": "CA",
                        "2": "MC"
                    },
                    "Admin": 0,
                    "Offsite": [
                        "CM",
                        "PM",
                        "FM",
                        "SK",
                        "CC",
                        "KC",
                        "TT",
                        "KK"
                    ]
                }
            },
            "20": {
                "Fri": {
                    "Call": {
                        "1": "DN",
                        "2": "MI"
                    },
                    "Admin": 0,
                    "Offsite": [
                        "MA",
                        "PM",
                        "FM",
                        "SK",
                        "CC",
                        "KC",
                        "TT",
                        "KK"
                    ]
                }
            },
            "21": {
                "Sat AM": {
                    "Call": {
                        "1": "RK",
                        "2": "MI"
                    },
                    "Admin": 0,
                    "Requests": "TI off",
                    "Offsite": [
                        "MA",
                        "MI"
                    ]
                },
                "Sat PM": {
                    "Call": {
                        "1": "MI",
                        "2": "RK"
                    },
                    "Admin": 0,
                    "Offsite": [
                        "MA"
                    ]
                }
            },
            "22": {
                "Sun AM": {
                    "Call": {
                        "1": "DN",
                        "2": "MI"
                    },
                    "Admin": 0,
                    "Offsite": [
                        "MA"
                    ]
                },
                "Sun PM": {
                    "Call": {
                        "1": "RK",
                        "2": "MI"
                    },
                    "Admin": 0,
                    "Offsite": [
                        "MA"
                    ]
                }
            },
            "23": {
                "Mon": {
                    "Call": {
                        "1": "JT",
                        "2": "TT"
                    },
                    "Admin": 0,
                    "Offsite": [
                        "KC",
                        "CC",
                        "SL",
                        "JM",
                        "RR",
                        "FM",
                        "SK",
                        "CA",
                        "MC",
                        "CM"
                    ]
                }
            },
            "24": {
                "Tue": {
                    "Call": {
                        "1": "KK",
                        "2": "ES"
                    },
                    "Admin": 0,
                    "Offsite": [
                        "JJ",
                        "JM",
                        "RR",
                        "FM",
                        "SK",
                        "CA",
                        "MC",
                        "CM"
                    ]
                }
            },
            "25": {
                "Wed": {
                    "Call": {
                        "1": "RK",
                        "2": "MI"
                    },
                    "Admin": 0,
                    "Offsite": [
                        "CC",
                        "JM",
                        "RR",
                        "FM",
                        "SK",
                        "CA",
                        "MC",
                        "CM"
                    ]
                }
            },
            "26": {
                "Thu": {
                    "Call": {
                        "1": "TI",
                        "2": "JT"
                    },
                    "Admin": 0,
                    "Requests": "MA on",
                    "Offsite": [
                        "MA",
                        "JM",
                        "RR",
                        "FM",
                        "SK",
                        "CA",
                        "MC",
                        "CM"
                    ]
                }
            },
            "27": {
                "Fri": {
                    "Call": {
                        "1": "TT",
                        "2": "ES"
                    },
                    "Admin": 0,
                    "Offsite": [
                        "KC",
                        "JM",
                        "RR",
                        "FM",
                        "SK",
                        "CA",
                        "MC",
                        "CM"
                    ]
                }
            },
            "28": {
                "Sat AM": {
                    "Call": {
                        "1": "KK",
                        "2": "ES"
                    },
                    "Admin": 0,
                    "Offsite": [
                        "KC"
                    ]
                },
                "Sat PM": {
                    "Call": {
                        "1": "ES",
                        "2": "KK"
                    },
                    "Admin": 0,
                    "Offsite": [
                        "KC"
                    ]
                }
            },
            "29": {
                "Sun AM": {
                    "Call": {
                        "1": "TT",
                        "2": "ES"
                    },
                    "Admin": 0,
                    "Offsite": [
                        "KC"
                    ]
                },
                "Sun PM": {
                    "Call": {
                        "1": "KK",
                        "2": "ES"
                    },
                    "Admin": 0,
                    "Offsite": [
                        "KC"
                    ]
                }
            }
        }
    }
}